datacatalog_custom_entries_manager/__init__.py
datacatalog_custom_entries_manager/constant.py
datacatalog_custom_entries_manager/custom_entries_csv_reader.py
datacatalog_custom_entries_manager/custom_entries_json_reader.py
datacatalog_custom_entries_manager/custom_entries_manager_cli.py
datacatalog_custom_entries_manager/custom_entries_synchronizer.py
datacatalog_custom_entries_manager/datacatalog_entry_factory.py
datacatalog_custom_entries_manager-0.1.2.dist-info/LICENSE
datacatalog_custom_entries_manager-0.1.2.dist-info/METADATA
datacatalog_custom_entries_manager-0.1.2.dist-info/WHEEL
datacatalog_custom_entries_manager-0.1.2.dist-info/entry_points.txt
datacatalog_custom_entries_manager-0.1.2.dist-info/top_level.txt
datacatalog_custom_entries_manager-0.1.2.dist-info/RECORD
